Typestrong/Typestrong.py
Typestrong/__init__.py
typestrong-1.0.0.dist-info/licenses/LICENSE
typestrong-1.0.0.dist-info/METADATA
typestrong-1.0.0.dist-info/WHEEL
typestrong-1.0.0.dist-info/top_level.txt
typestrong-1.0.0.dist-info/RECORD
