Metadata-Version: 2.4
Name: Typestrong
Version: 1.0.0
Summary: Enforce Typehints at Runtime
Author-email: Phillip Harry T <philliptinsley44@gmail.com>
License: Apache NON-AI License, Version 2.0
Keywords: strongly typed,strictly typed,typehint,typescript,Literal,enforce
Classifier: License :: Other/Proprietary License
Classifier: Programming Language :: Python
Classifier: Programming Language :: Python :: 3
Classifier: Intended Audience :: Information Technology
Requires-Python: >=3.8
License-File: LICENSE
Dynamic: license-file
